datastoreflex/__init__.py
datastoreflex/client.py
datastoreflex-0.5.0.dist-info/LICENSE
datastoreflex-0.5.0.dist-info/METADATA
datastoreflex-0.5.0.dist-info/WHEEL
datastoreflex-0.5.0.dist-info/top_level.txt
datastoreflex-0.5.0.dist-info/RECORD
