Metadata-Version: 2.1
Name: datastoreflex
Version: 0.5.0
Summary: Messging Client
Home-page: https://github.com/seung-lab/datastore-flex
Author: Akhilesh Halageri
Project-URL: Bug Tracker, https://github.com/seung-lab/datastore-flex/issues
Classifier: Programming Language :: Python :: 3
Classifier: License :: OSI Approved :: MIT License
Classifier: Operating System :: OS Independent
Requires-Python: >=3.6
License-File: LICENSE
Requires-Dist: google-cloud-datastore
Requires-Dist: cloud-files
